hanzo_tools/__init__.py
hanzo_tools/computer/__init__.py
hanzo_tools/computer/computer_tool.py
hanzo_tools_computer-0.2.0.dist-info/METADATA
hanzo_tools_computer-0.2.0.dist-info/WHEEL
hanzo_tools_computer-0.2.0.dist-info/entry_points.txt
hanzo_tools_computer-0.2.0.dist-info/RECORD
