Metadata-Version: 2.4
Name: hanzo-tools-computer
Version: 0.2.0
Summary: Computer control tools for Hanzo AI - pyautogui-based Mac automation
Author-email: Hanzo AI <dev@hanzo.ai>
License-Expression: MIT
Keywords: ai,automation,computer,hanzo,mcp,pyautogui,tools
Classifier: Development Status :: 4 - Beta
Classifier: Intended Audience :: Developers
Classifier: License :: OSI Approved :: MIT License
Classifier: Programming Language :: Python :: 3
Classifier: Programming Language :: Python :: 3.11
Classifier: Programming Language :: Python :: 3.12
Classifier: Programming Language :: Python :: 3.13
Requires-Python: >=3.11
Requires-Dist: hanzo-tools-core>=0.1.0
Requires-Dist: mcp>=1.25.0
Requires-Dist: pillow>=10.0.0
Requires-Dist: pyautogui>=0.9.54
Requires-Dist: pydantic>=2.0.0
Provides-Extra: dev
Requires-Dist: pytest-asyncio>=0.24.0; extra == 'dev'
Requires-Dist: pytest>=8.0.0; extra == 'dev'
